<?xml version="1.0" encoding="utf-8"?>
<doctrine-mapping xmlns="http://doctrine-project.org/schemas/orm/doctrine-mapping" xmlns:xsi="http://www.w3.org/2001/XMLSchema-instance" xsi:schemaLocation="http://doctrine-project.org/schemas/orm/doctrine-mapping http://doctrine-project.org/schemas/orm/doctrine-mapping.xsd">
  <entity name="MdlMnetService2rpc" table="mdl_mnet_service2rpc">
    <unique-constraints>
      <unique-constraint name="mdl_mnetserv_rpcser_uix" columns="rpcid,serviceid"/>
    </unique-constraints>
    <id name="id" type="bigint" column="id">
      <generator strategy="IDENTITY"/>
    </id>
    <field name="serviceid" type="bigint" column="serviceid" nullable="false"/>
    <field name="rpcid" type="bigint" column="rpcid" nullable="false"/>
  </entity>
</doctrine-mapping>
